{
  "unversionedId": "Biblia/Pregacoes/a-cruz",
  "id": "Biblia/Pregacoes/a-cruz",
  "title": "A Cruz",
  "description": "Texto Fundamental:",
  "source": "@site/docs/Biblia/Pregacoes/a-cruz.md",
  "sourceDirName": "Biblia/Pregacoes",
  "slug": "/Biblia/Pregacoes/a-cruz",
  "permalink": "/docs/Biblia/Pregacoes/a-cruz",
  "draft": false,
  "editUrl": "https://github.com/facebook/docusaurus/tree/main/packages/create-docusaurus/templates/shared/docs/Biblia/Pregacoes/a-cruz.md",
  "tags": [],
  "version": "current",
  "frontMatter": {
    "id": "a-cruz",
    "title": "A Cruz",
    "date": "19-07-2021"
  },
  "sidebar": "tutorialSidebar",
  "previous": {
    "title": "A conversão de Paulo",
    "permalink": "/docs/Biblia/Pregacoes/a-conversao-de-paulo"
  },
  "next": {
    "title": "A oração de Jabez",
    "permalink": "/docs/Biblia/Pregacoes/a-oracao-de-jabez"
  }
}